imcp/__init__.py
imcp/imcp.py
imcp-1.0.1.dist-info/LICENSE
imcp-1.0.1.dist-info/METADATA
imcp-1.0.1.dist-info/WHEEL
imcp-1.0.1.dist-info/top_level.txt
imcp-1.0.1.dist-info/RECORD
