Metadata-Version: 2.1
Name: imcp
Version: 1.0.1
Summary: Imbalanced Multiclass Classification Performance Curve
Home-page: https://github.com/adaa-polsl/imcp
Author: Łukasz Wróbel, Bartosz Piguła
Classifier: Development Status :: 5 - Production/Stable
Classifier: License :: OSI Approved :: BSD License
Classifier: Programming Language :: Python :: 3
Classifier: Operating System :: Microsoft :: Windows
Classifier: Operating System :: Unix
Classifier: Topic :: Scientific/Engineering
Classifier: Topic :: Scientific/Engineering :: Artificial Intelligence
Classifier: Intended Audience :: Developers
Classifier: Intended Audience :: Science/Research
Requires-Python: >=3.6
License-File: LICENSE
Requires-Dist: numpy
Requires-Dist: matplotlib
